ktlkit/__init__.py
ktlkit/ktlkit.py
ktlkit-0.0.1.dist-info/METADATA
ktlkit-0.0.1.dist-info/WHEEL
ktlkit-0.0.1.dist-info/licenses/LICENSE
ktlkit-0.0.1.dist-info/RECORD
