Metadata-Version: 2.3
Name: KTLKit
Version: 0.0.1
Summary: Kotlin-like thing in python!
Project-URL: Homepage, https://github.com/DinoJw/KTLKit
Project-URL: Issues, https://github.com/DinoJw/KTLKit/issues
Author: DinoJw
License-File: LICENSE
Classifier: License :: OSI Approved :: MIT License
Classifier: Operating System :: OS Independent
Classifier: Programming Language :: Python :: 3
Requires-Python: >=3.8
